piltools/__init__.py
piltools/transform.py
piltools/test/__init__.py
piltools/test/test_transform.py
piltools-0.0.4.dist-info/LICENSE
piltools-0.0.4.dist-info/METADATA
piltools-0.0.4.dist-info/WHEEL
piltools-0.0.4.dist-info/top_level.txt
piltools-0.0.4.dist-info/RECORD
