Metadata-Version: 2.1
Name: piltools
Version: 0.0.4
Summary: Tool suite that augments existing Python Imaging Library
Home-page: https://github.com/GregWasHere/PILTools
Author: Greg Krause
Author-email: gregckrause@gmail.com
License: UNKNOWN
Project-URL: Bug Tracker, https://github.com/GregWasHere/PILTools/issues
Platform: UNKNOWN
Classifier: Programming Language :: Python :: 3
Classifier: License :: OSI Approved :: BSD License
Classifier: Operating System :: OS Independent
Requires-Python: >=3.6
License-File: LICENSE
Requires-Dist: Pillow (==8.2.0)
